[{"niceName":"accompagnements","region":"FR-ICOOKIN","visibility":true,"name":"Accompagnements","count":571,"mineCount":0,"draftCount":0,"favoritesCount":0,"checkedCount":24,"toDoCount":0,"doneCount":0},{"niceName":"aperitifs","region":"FR-ICOOKIN","name":"Apéritifs","visibility":true,"count":972,"mineCount":0,"draftCount":0,"favoritesCount":0,"checkedCount":24,"toDoCount":0,"doneCount":0},{"niceName":"autres","name":"Autres","region":"FR-ICOOKIN","visibility":true,"count":349,"mineCount":0,"draftCount":0,"favoritesCount":0,"checkedCount":3,"toDoCount":0,"doneCount":0},{"niceName":"boissons","region":"FR-ICOOKIN","visibility":true,"name":"Boissons","count":334,"mineCount":0,"draftCount":0,"favoritesCount":0,"checkedCount":18,"toDoCount":0,"doneCount":0},{"niceName":"boulangerie","region":"FR-ICOOKIN","name":"Boulangerie","visibility":true,"count":936,"mineCount":0,"draftCount":0,"favoritesCount":0,"checkedCount":14,"toDoCount":0,"doneCount":0},{"niceName":"cakes-et-quiches","region":"FR-ICOOKIN","name":"Cakes et quiches salés","visibility":true,"count":90,"mineCount":0,"draftCount":0,"favoritesCount":0,"checkedCount":0,"toDoCount":0,"doneCount":0},{"niceName":"desserts","region":"FR-ICOOKIN","visibility":true,"name":"Desserts","count":4308,"mineCount":0,"draftCount":0,"favoritesCount":0,"checkedCount":157,"toDoCount":0,"doneCount":0},{"niceName":"entrees","region":"FR-ICOOKIN","name":"Entrées","visibility":true,"count":617,"mineCount":0,"draftCount":0,"favoritesCount":0,"checkedCount":21,"toDoCount":0,"doneCount":0},{"niceName":"glaces-et-sorbets","visibility":true,"name":"Glaces et sorbets","region":"FR-ICOOKIN","count":188,"mineCount":0,"draftCount":0,"favoritesCount":0,"checkedCount":19,"toDoCount":0,"doneCount":0},{"niceName":"plats","region":"FR-ICOOKIN","visibility":true,"name":"Plats","count":1498,"mineCount":0,"draftCount":0,"favoritesCount":0,"checkedCount":124,"toDoCount":0,"doneCount":0},{"niceName":"pates","region":"FR-ICOOKIN","visibility":true,"name":"Pâtes","count":8,"mineCount":0,"draftCount":0,"favoritesCount":0,"checkedCount":7,"toDoCount":0,"doneCount":0},{"niceName":"sauces","region":"FR-ICOOKIN","visibility":true,"name":"Sauces","count":337,"mineCount":0,"draftCount":0,"favoritesCount":0,"checkedCount":28,"toDoCount":0,"doneCount":0},{"niceName":"soupes-et-cremes","region":"FR-ICOOKIN","visibility":true,"name":"Soupes et crèmes","count":719,"mineCount":0,"draftCount":0,"favoritesCount":0,"checkedCount":30,"toDoCount":0,"doneCount":0}]